CwmpClient/__init__.py
CwmpClient/__main__.py
CwmpClient/helpers.py
CwmpClient/nodes.py
CwmpClient/plugins/__init__.py
CwmpClient/plugins/tr069.py
CwmpClient-0.0.1b0.dist-info/LICENSE
CwmpClient-0.0.1b0.dist-info/METADATA
CwmpClient-0.0.1b0.dist-info/WHEEL
CwmpClient-0.0.1b0.dist-info/top_level.txt
CwmpClient-0.0.1b0.dist-info/RECORD
